{
  "timestamp": "2025-06-05T11:53:27.469503",
  "name": "Painted Prairie",
  "status": null,
  "url": "https://www.pulte.com/homes/colorado/denver/aurora/painted-prairie-211358",
  "price_from": "$459,990",
  "address": "21244 E 63rd Dr, Aurora, Colorado 80019",
  "phone": "(720) 815-0471",
  "description": "ABOUT THE HOME ENERGY RATING SCALE\nThe HERS (Home Energy Rating System) Index allows buyers to compare the relative energy efficiency of different homes. The HERS Index home energy rating is determined by an independent RESNET-certified home energy rater (\"Rater\"). The lower a home&rsquo;s score, the more energy efficient it is in comparison to the HERS referenced home. For every one-point decrease in the HERS Index score, there is a corresponding one percent (1%) reduction in energy consumption as compared to a home with a HERS Index of 100. A home with a HERS score of 100 reflects a home built to 2006 IEEC Building Codes. See the bottom of this page for more information on HERS scores.",
  "images": [
    "https://res.cloudinary.com/dv0jqjrc3/image/fetch/ar_1.5,c_fill,f_auto,q_auto,w_768/https://pultegroup.cdn.picturepark.com/v/im9C6SVu/"
  ],
  "location": {
    "latitude": 39.811775,
    "longitude": -104.738848,
    "address": {
      "city": null,
      "state": null,
      "market": null
    }
  },
  "details": {
    "price_range": "$459,990-$517,990",
    "sqft_range": "1,651-2,069",
    "bed_range": "3-4",
    "bath_range": "2.5-3.0",
    "stories_range": "2",
    "community_count": 1
  },
  "amenities": [],
  "homeplans": [
    {
      "name": "Arrabelle",
      "url": "https://www.pulte.com/homes/colorado/denver/aurora/painted-prairie-211358/arrabelle-698416",
      "details": {
        "price": "From $459,990",
        "beds": "3 bd",
        "baths": "2.5 ba",
        "half_baths": null,
        "sqft": "1,651 ft²",
        "status": "Actively selling",
        "image_url": "https://res.cloudinary.com/dv0jqjrc3/image/fetch/ar_1.5,c_fill,f_auto,q_auto,g_north,w_132,f_auto,q_auto/https://pultegroup.picturepark.com/Go/zik55UlN/V/677318/1"
      },
      "floorplan_images": [
        {
          "name": "1st Floor Floorplan",
          "url": "https://res.cloudinary.com/dv0jqjrc3/image/fetch/ar_1.0,c_fill,q_auto,f_auto/https://pultegroup.picturepark.com/Go/SALUEzBm/V/662909/1"
        },
        {
          "name": "2nd Floor Floorplan",
          "url": "https://res.cloudinary.com/dv0jqjrc3/image/fetch/ar_1.0,c_fill,q_auto,f_auto/https://pultegroup.picturepark.com/Go/SALUEzBm/V/662911/1"
        }
      ]
    },
    {
      "name": "Blake",
      "url": "https://www.pulte.com/homes/colorado/denver/aurora/painted-prairie-211358/blake-698417",
      "details": {
        "price": "From $474,990",
        "beds": "3 bd",
        "baths": "2.5 ba",
        "half_baths": null,
        "sqft": "1,873 ft²",
        "status": "Actively selling",
        "image_url": "https://res.cloudinary.com/dv0jqjrc3/image/fetch/ar_1.5,c_fill,f_auto,q_auto,g_north,w_132,f_auto,q_auto/https://pultegroup.picturepark.com/Go/g3D9d54M/V/677322/1"
      },
      "floorplan_images": [
        {
          "name": "1st Floor Floorplan",
          "url": "https://res.cloudinary.com/dv0jqjrc3/image/fetch/ar_1.0,c_fill,q_auto,f_auto/https://pultegroup.picturepark.com/Go/xUr9Zx0x/V/662910/1"
        },
        {
          "name": "2nd Floor Floorplan",
          "url": "https://res.cloudinary.com/dv0jqjrc3/image/fetch/ar_1.0,c_fill,q_auto,f_auto/https://pultegroup.picturepark.com/Go/xUr9Zx0x/V/662913/1"
        }
      ]
    },
    {
      "name": "Perry",
      "url": "https://www.pulte.com/homes/colorado/denver/aurora/painted-prairie-211358/perry-698418",
      "details": {
        "price": "From $504,990",
        "beds": "3 bd",
        "baths": "2.5 ba",
        "half_baths": null,
        "sqft": "2,065 ft²",
        "status": "Actively selling",
        "image_url": "https://res.cloudinary.com/dv0jqjrc3/image/fetch/ar_1.5,c_fill,f_auto,q_auto,g_north,w_132,f_auto,q_auto/https://pultegroup.cdn.picturepark.com/v/pJY78x4S/"
      },
      "floorplan_images": [
        {
          "name": "1st Floor Floorplan",
          "url": "https://res.cloudinary.com/dv0jqjrc3/image/fetch/ar_1.0,c_fill,q_auto,f_auto/https://pultegroup.picturepark.com/Go/vYVe04Cv/V/662912/1"
        },
        {
          "name": "2nd Floor Floorplan",
          "url": "https://res.cloudinary.com/dv0jqjrc3/image/fetch/ar_1.0,c_fill,q_auto,f_auto/https://pultegroup.picturepark.com/Go/vYVe04Cv/V/662914/1"
        }
      ]
    },
    {
      "name": "Rowen",
      "url": "https://www.pulte.com/homes/colorado/denver/aurora/painted-prairie-211358/rowen-698419",
      "details": {
        "price": "From $509,990",
        "beds": "4 bd",
        "baths": "3 ba",
        "half_baths": null,
        "sqft": "2,069 ft²",
        "status": "Actively selling",
        "image_url": "https://res.cloudinary.com/dv0jqjrc3/image/fetch/ar_1.5,c_fill,f_auto,q_auto,g_north,w_132,f_auto,q_auto/https://pultegroup.picturepark.com/Go/sX3iOZau/V/677331/1"
      },
      "floorplan_images": [
        {
          "name": "1st Floor Floorplan",
          "url": "https://res.cloudinary.com/dv0jqjrc3/image/fetch/ar_1.0,c_fill,q_auto,f_auto/https://pultegroup.picturepark.com/Go/Db0jHnf1/V/662915/1"
        },
        {
          "name": "2nd Floor Floorplan",
          "url": "https://res.cloudinary.com/dv0jqjrc3/image/fetch/ar_1.0,c_fill,q_auto,f_auto/https://pultegroup.picturepark.com/Go/Db0jHnf1/V/662916/1"
        }
      ]
    },
    {
      "name": "Caroline",
      "url": "https://www.pulte.com/homes/colorado/denver/aurora/painted-prairie-211358/caroline-698415",
      "details": {
        "price": "From $517,990",
        "beds": "3 bd",
        "baths": "2.5 ba",
        "half_baths": null,
        "sqft": "1,997 ft²",
        "status": "Actively selling",
        "image_url": "https://res.cloudinary.com/dv0jqjrc3/image/fetch/ar_1.5,c_fill,f_auto,q_auto,g_north,w_132,f_auto,q_auto/https://pultegroup.picturepark.com/Go/3BqWlSa9/V/677325/1"
      },
      "floorplan_images": [
        {
          "name": "1st Floor Floorplan",
          "url": "https://res.cloudinary.com/dv0jqjrc3/image/fetch/ar_1.0,c_fill,q_auto,f_auto/https://pultegroup.picturepark.com/Go/BClACyZK/V/662917/1"
        },
        {
          "name": "2nd Floor Floorplan",
          "url": "https://res.cloudinary.com/dv0jqjrc3/image/fetch/ar_1.0,c_fill,q_auto,f_auto/https://pultegroup.picturepark.com/Go/BClACyZK/V/662908/1"
        }
      ]
    }
  ],
  "homesites": [
    {
      "name": "21244 E 63rd Dr",
      "plan": "Arrabelle",
      "id": "698416",
      "address": "21244 E 63rd Dr, Aurora, Colorado",
      "price": "$459,990",
      "beds": "3 bd",
      "baths": "2.5 ba",
      "sqft": "1,651 ft²",
      "status": "Available",
      "image_url": "https://res.cloudinary.com/dv0jqjrc3/image/fetch/ar_1.5,c_fill,f_auto,q_auto,g_north,w_132,f_auto,q_auto/https://pultegroup.picturepark.com/Go/zik55UlN/V/677318/1",
      "url": "https://www.pulte.com/homes/colorado/denver/aurora/painted-prairie-211358/arrabelle-698416",
      "latitude": 27.3646311523029,
      "longitude": -82.3959473004829,
      "overview": "ABOUT THE HOME ENERGY RATING SCALE\nThe HERS (Home Energy Rating System) Index allows buyers to compare the relative energy efficiency of different homes. The HERS Index home energy rating is determined by an independent RESNET-certified home energy rater (\"Rater\"). The lower a home&rsquo;s score, the more energy efficient it is in comparison to the HERS referenced home. For every one-point decrease in the HERS Index score, there is a corresponding one percent (1%) reduction in energy consumption as compared to a home with a HERS Index of 100. A home with a HERS score of 100 reflects a home built to 2006 IEEC Building Codes. See the bottom of this page for more information on HERS scores.",
      "images": [
        "https://res.cloudinary.com/dv0jqjrc3/image/fetch/ar_1.5,c_fill,f_auto,q_auto,w_auto,f_auto,q_auto/https://pultegroup.picturepark.com/Go/zik55UlN/V/677321/1",
        "https://res.cloudinary.com/dv0jqjrc3/image/fetch/ar_1.5,c_fill,f_auto,q_auto,w_auto,f_auto,q_auto/https://pultegroup.cdn.picturepark.com/v/LXjlP0T8/",
        "https://res.cloudinary.com/dv0jqjrc3/image/fetch/ar_1.5,c_fill,f_auto,q_auto,w_auto,f_auto,q_auto/https://pultegroup.cdn.picturepark.com/v/pmM6sGBx/",
        "https://res.cloudinary.com/dv0jqjrc3/image/fetch/ar_1.5,c_fill,f_auto,q_auto,w_auto,f_auto,q_auto/https://pultegroup.cdn.picturepark.com/v/u1MAIAuo/",
        "https://res.cloudinary.com/dv0jqjrc3/image/fetch/ar_1.5,c_fill,f_auto,q_auto,w_auto,f_auto,q_auto/https://pultegroup.picturepark.com/Go/zik55UlN/V/677318/1",
        "https://res.cloudinary.com/dv0jqjrc3/image/fetch/ar_1.5,c_fill,f_auto,q_auto,w_auto,f_auto,q_auto/https://pultegroup.cdn.picturepark.com/v/Idjj4Nsq/",
        "https://res.cloudinary.com/dv0jqjrc3/image/fetch/ar_1.5,c_fill,f_auto,q_auto,w_auto,f_auto,q_auto/https://pultegroup.cdn.picturepark.com/v/XSzpvn9M/",
        "https://res.cloudinary.com/dv0jqjrc3/image/fetch/ar_1.5,c_fill,f_auto,q_auto,w_auto,f_auto,q_auto/https://pultegroup.picturepark.com/Go/zik55UlN/V/677320/1",
        "https://res.cloudinary.com/dv0jqjrc3/image/fetch/ar_1.5,c_fill,f_auto,q_auto,w_auto,f_auto,q_auto/https://pultegroup.picturepark.com/Go/zik55UlN/V/677321/1",
        "https://res.cloudinary.com/dv0jqjrc3/image/fetch/ar_1.5,c_fill,f_auto,q_auto,w_auto,f_auto,q_auto/https://pultegroup.cdn.picturepark.com/v/LXjlP0T8/",
        "https://res.cloudinary.com/dv0jqjrc3/image/fetch/ar_1.5,c_fill,f_auto,q_auto,w_auto,f_auto,q_auto/https://pultegroup.cdn.picturepark.com/v/pmM6sGBx/",
        "https://res.cloudinary.com/dv0jqjrc3/image/fetch/ar_1.5,c_fill,f_auto,q_auto,w_auto,f_auto,q_auto/https://pultegroup.cdn.picturepark.com/v/u1MAIAuo/",
        "https://res.cloudinary.com/dv0jqjrc3/image/fetch/ar_1.5,c_fill,f_auto,q_auto,w_auto,f_auto,q_auto/https://pultegroup.picturepark.com/Go/zik55UlN/V/677318/1",
        "https://res.cloudinary.com/dv0jqjrc3/image/fetch/ar_1.5,c_fill,f_auto,q_auto,w_auto,f_auto,q_auto/https://pultegroup.cdn.picturepark.com/v/Idjj4Nsq/",
        "https://res.cloudinary.com/dv0jqjrc3/image/fetch/ar_1.5,c_fill,f_auto,q_auto,w_auto,f_auto,q_auto/https://pultegroup.cdn.picturepark.com/v/XSzpvn9M/",
        "https://res.cloudinary.com/dv0jqjrc3/image/fetch/ar_1.5,c_fill,f_auto,q_auto,w_auto,f_auto,q_auto/https://pultegroup.picturepark.com/Go/zik55UlN/V/677320/1",
        "https://res.cloudinary.com/dv0jqjrc3/image/fetch/ar_1.5,c_fill,f_auto,q_auto,w_auto,f_auto,q_auto/https://pultegroup.picturepark.com/Go/zik55UlN/V/677321/1"
      ]
    },
    {
      "name": "21244 E 63rd Dr",
      "plan": "Blake",
      "id": "698417",
      "address": "21244 E 63rd Dr, Aurora, Colorado",
      "price": "$474,990",
      "beds": "3 bd",
      "baths": "2.5 ba",
      "sqft": "1,873 ft²",
      "status": "Available",
      "image_url": "https://res.cloudinary.com/dv0jqjrc3/image/fetch/ar_1.5,c_fill,f_auto,q_auto,g_north,w_132,f_auto,q_auto/https://pultegroup.picturepark.com/Go/g3D9d54M/V/677322/1",
      "url": "https://www.pulte.com/homes/colorado/denver/aurora/painted-prairie-211358/blake-698417",
      "latitude": 27.3646311523029,
      "longitude": -82.3959473004829,
      "overview": "ABOUT THE HOME ENERGY RATING SCALE\nThe HERS (Home Energy Rating System) Index allows buyers to compare the relative energy efficiency of different homes. The HERS Index home energy rating is determined by an independent RESNET-certified home energy rater (\"Rater\"). The lower a home&rsquo;s score, the more energy efficient it is in comparison to the HERS referenced home. For every one-point decrease in the HERS Index score, there is a corresponding one percent (1%) reduction in energy consumption as compared to a home with a HERS Index of 100. A home with a HERS score of 100 reflects a home built to 2006 IEEC Building Codes. See the bottom of this page for more information on HERS scores.",
      "images": [
        "https://res.cloudinary.com/dv0jqjrc3/image/fetch/ar_1.5,c_fill,f_auto,q_auto,w_auto,f_auto,q_auto/https://pultegroup.picturepark.com/Go/g3D9d54M/V/677324/1",
        "https://res.cloudinary.com/dv0jqjrc3/image/fetch/ar_1.5,c_fill,f_auto,q_auto,w_auto,f_auto,q_auto/https://pultegroup.cdn.picturepark.com/v/CHzZBDmB/",
        "https://res.cloudinary.com/dv0jqjrc3/image/fetch/ar_1.5,c_fill,f_auto,q_auto,w_auto,f_auto,q_auto/https://pultegroup.cdn.picturepark.com/v/FYLIqFCx/",
        "https://res.cloudinary.com/dv0jqjrc3/image/fetch/ar_1.5,c_fill,f_auto,q_auto,w_auto,f_auto,q_auto/https://pultegroup.cdn.picturepark.com/v/6ZD28xXO/",
        "https://res.cloudinary.com/dv0jqjrc3/image/fetch/ar_1.5,c_fill,f_auto,q_auto,w_auto,f_auto,q_auto/https://pultegroup.picturepark.com/Go/g3D9d54M/V/677322/1",
        "https://res.cloudinary.com/dv0jqjrc3/image/fetch/ar_1.5,c_fill,f_auto,q_auto,w_auto,f_auto,q_auto/https://pultegroup.cdn.picturepark.com/v/EgFS7RLz/",
        "https://res.cloudinary.com/dv0jqjrc3/image/fetch/ar_1.5,c_fill,f_auto,q_auto,w_auto,f_auto,q_auto/https://pultegroup.cdn.picturepark.com/v/Ip4mWGNV/",
        "https://res.cloudinary.com/dv0jqjrc3/image/fetch/ar_1.5,c_fill,f_auto,q_auto,w_auto,f_auto,q_auto/https://pultegroup.picturepark.com/Go/g3D9d54M/V/677323/1",
        "https://res.cloudinary.com/dv0jqjrc3/image/fetch/ar_1.5,c_fill,f_auto,q_auto,w_auto,f_auto,q_auto/https://pultegroup.picturepark.com/Go/g3D9d54M/V/677324/1",
        "https://res.cloudinary.com/dv0jqjrc3/image/fetch/ar_1.5,c_fill,f_auto,q_auto,w_auto,f_auto,q_auto/https://pultegroup.cdn.picturepark.com/v/CHzZBDmB/",
        "https://res.cloudinary.com/dv0jqjrc3/image/fetch/ar_1.5,c_fill,f_auto,q_auto,w_auto,f_auto,q_auto/https://pultegroup.cdn.picturepark.com/v/FYLIqFCx/",
        "https://res.cloudinary.com/dv0jqjrc3/image/fetch/ar_1.5,c_fill,f_auto,q_auto,w_auto,f_auto,q_auto/https://pultegroup.cdn.picturepark.com/v/6ZD28xXO/",
        "https://res.cloudinary.com/dv0jqjrc3/image/fetch/ar_1.5,c_fill,f_auto,q_auto,w_auto,f_auto,q_auto/https://pultegroup.picturepark.com/Go/g3D9d54M/V/677322/1",
        "https://res.cloudinary.com/dv0jqjrc3/image/fetch/ar_1.5,c_fill,f_auto,q_auto,w_auto,f_auto,q_auto/https://pultegroup.cdn.picturepark.com/v/EgFS7RLz/",
        "https://res.cloudinary.com/dv0jqjrc3/image/fetch/ar_1.5,c_fill,f_auto,q_auto,w_auto,f_auto,q_auto/https://pultegroup.cdn.picturepark.com/v/Ip4mWGNV/",
        "https://res.cloudinary.com/dv0jqjrc3/image/fetch/ar_1.5,c_fill,f_auto,q_auto,w_auto,f_auto,q_auto/https://pultegroup.picturepark.com/Go/g3D9d54M/V/677323/1",
        "https://res.cloudinary.com/dv0jqjrc3/image/fetch/ar_1.5,c_fill,f_auto,q_auto,w_auto,f_auto,q_auto/https://pultegroup.picturepark.com/Go/g3D9d54M/V/677324/1"
      ]
    },
    {
      "name": "21244 E 63rd Dr",
      "plan": "Perry",
      "id": "698418",
      "address": "21244 E 63rd Dr, Aurora, Colorado",
      "price": "$504,990",
      "beds": "3 bd",
      "baths": "2.5 ba",
      "sqft": "2,065 ft²",
      "status": "Available",
      "image_url": "https://res.cloudinary.com/dv0jqjrc3/image/fetch/ar_1.5,c_fill,f_auto,q_auto,g_north,w_132,f_auto,q_auto/https://pultegroup.cdn.picturepark.com/v/pJY78x4S/",
      "url": "https://www.pulte.com/homes/colorado/denver/aurora/painted-prairie-211358/perry-698418",
      "latitude": 27.3646311523029,
      "longitude": -82.3959473004829,
      "overview": "ABOUT THE HOME ENERGY RATING SCALE\nThe HERS (Home Energy Rating System) Index allows buyers to compare the relative energy efficiency of different homes. The HERS Index home energy rating is determined by an independent RESNET-certified home energy rater (\"Rater\"). The lower a home&rsquo;s score, the more energy efficient it is in comparison to the HERS referenced home. For every one-point decrease in the HERS Index score, there is a corresponding one percent (1%) reduction in energy consumption as compared to a home with a HERS Index of 100. A home with a HERS score of 100 reflects a home built to 2006 IEEC Building Codes. See the bottom of this page for more information on HERS scores.",
      "images": [
        "https://res.cloudinary.com/dv0jqjrc3/image/fetch/ar_1.5,c_fill,f_auto,q_auto,w_auto,f_auto,q_auto/https://pultegroup.picturepark.com/Go/HjyaiSaR/V/677329/1",
        "https://res.cloudinary.com/dv0jqjrc3/image/fetch/ar_1.5,c_fill,f_auto,q_auto,w_auto,f_auto,q_auto/https://pultegroup.picturepark.com/Go/HjyaiSaR/V/677330/1",
        "https://res.cloudinary.com/dv0jqjrc3/image/fetch/ar_1.5,c_fill,f_auto,q_auto,w_auto,f_auto,q_auto/https://pultegroup.cdn.picturepark.com/v/JzheQvO9/",
        "https://res.cloudinary.com/dv0jqjrc3/image/fetch/ar_1.5,c_fill,f_auto,q_auto,w_auto,f_auto,q_auto/https://pultegroup.cdn.picturepark.com/v/lAcJPsnY/",
        "https://res.cloudinary.com/dv0jqjrc3/image/fetch/ar_1.5,c_fill,f_auto,q_auto,w_auto,f_auto,q_auto/https://pultegroup.cdn.picturepark.com/v/aA3Ty4FD/",
        "https://res.cloudinary.com/dv0jqjrc3/image/fetch/ar_1.5,c_fill,f_auto,q_auto,w_auto,f_auto,q_auto/https://pultegroup.cdn.picturepark.com/v/pJY78x4S/",
        "https://res.cloudinary.com/dv0jqjrc3/image/fetch/ar_1.5,c_fill,f_auto,q_auto,w_auto,f_auto,q_auto/https://pultegroup.cdn.picturepark.com/v/oOwFquPc/",
        "https://res.cloudinary.com/dv0jqjrc3/image/fetch/ar_1.5,c_fill,f_auto,q_auto,w_auto,f_auto,q_auto/https://pultegroup.cdn.picturepark.com/v/lmtxa7JW/",
        "https://res.cloudinary.com/dv0jqjrc3/image/fetch/ar_1.5,c_fill,f_auto,q_auto,w_auto,f_auto,q_auto/https://pultegroup.cdn.picturepark.com/v/ZUrt0HBA/",
        "https://res.cloudinary.com/dv0jqjrc3/image/fetch/ar_1.5,c_fill,f_auto,q_auto,w_auto,f_auto,q_auto/https://pultegroup.cdn.picturepark.com/v/dki2MMqB/",
        "https://res.cloudinary.com/dv0jqjrc3/image/fetch/ar_1.5,c_fill,f_auto,q_auto,w_auto,f_auto,q_auto/https://pultegroup.picturepark.com/Go/HjyaiSaR/V/677328/1",
        "https://res.cloudinary.com/dv0jqjrc3/image/fetch/ar_1.5,c_fill,f_auto,q_auto,w_auto,f_auto,q_auto/https://pultegroup.picturepark.com/Go/HjyaiSaR/V/677329/1",
        "https://res.cloudinary.com/dv0jqjrc3/image/fetch/ar_1.5,c_fill,f_auto,q_auto,w_auto,f_auto,q_auto/https://pultegroup.picturepark.com/Go/HjyaiSaR/V/677330/1",
        "https://res.cloudinary.com/dv0jqjrc3/image/fetch/ar_1.5,c_fill,f_auto,q_auto,w_auto,f_auto,q_auto/https://pultegroup.cdn.picturepark.com/v/JzheQvO9/",
        "https://res.cloudinary.com/dv0jqjrc3/image/fetch/ar_1.5,c_fill,f_auto,q_auto,w_auto,f_auto,q_auto/https://pultegroup.cdn.picturepark.com/v/lAcJPsnY/",
        "https://res.cloudinary.com/dv0jqjrc3/image/fetch/ar_1.5,c_fill,f_auto,q_auto,w_auto,f_auto,q_auto/https://pultegroup.cdn.picturepark.com/v/aA3Ty4FD/",
        "https://res.cloudinary.com/dv0jqjrc3/image/fetch/ar_1.5,c_fill,f_auto,q_auto,w_auto,f_auto,q_auto/https://pultegroup.cdn.picturepark.com/v/pJY78x4S/",
        "https://res.cloudinary.com/dv0jqjrc3/image/fetch/ar_1.5,c_fill,f_auto,q_auto,w_auto,f_auto,q_auto/https://pultegroup.cdn.picturepark.com/v/oOwFquPc/",
        "https://res.cloudinary.com/dv0jqjrc3/image/fetch/ar_1.5,c_fill,f_auto,q_auto,w_auto,f_auto,q_auto/https://pultegroup.cdn.picturepark.com/v/lmtxa7JW/",
        "https://res.cloudinary.com/dv0jqjrc3/image/fetch/ar_1.5,c_fill,f_auto,q_auto,w_auto,f_auto,q_auto/https://pultegroup.cdn.picturepark.com/v/ZUrt0HBA/",
        "https://res.cloudinary.com/dv0jqjrc3/image/fetch/ar_1.5,c_fill,f_auto,q_auto,w_auto,f_auto,q_auto/https://pultegroup.cdn.picturepark.com/v/dki2MMqB/",
        "https://res.cloudinary.com/dv0jqjrc3/image/fetch/ar_1.5,c_fill,f_auto,q_auto,w_auto,f_auto,q_auto/https://pultegroup.picturepark.com/Go/HjyaiSaR/V/677328/1"
      ]
    },
    {
      "name": "21244 E 63rd Dr",
      "plan": "Rowen",
      "id": "698419",
      "address": "21244 E 63rd Dr, Aurora, Colorado",
      "price": "$509,990",
      "beds": "4 bd",
      "baths": "3 ba",
      "sqft": "2,069 ft²",
      "status": "Available",
      "image_url": "https://res.cloudinary.com/dv0jqjrc3/image/fetch/ar_1.5,c_fill,f_auto,q_auto,g_north,w_132,f_auto,q_auto/https://pultegroup.picturepark.com/Go/sX3iOZau/V/677331/1",
      "url": "https://www.pulte.com/homes/colorado/denver/aurora/painted-prairie-211358/rowen-698419",
      "latitude": 27.3646311523029,
      "longitude": -82.3959473004829,
      "overview": "ABOUT THE HOME ENERGY RATING SCALE\nThe HERS (Home Energy Rating System) Index allows buyers to compare the relative energy efficiency of different homes. The HERS Index home energy rating is determined by an independent RESNET-certified home energy rater (\"Rater\"). The lower a home&rsquo;s score, the more energy efficient it is in comparison to the HERS referenced home. For every one-point decrease in the HERS Index score, there is a corresponding one percent (1%) reduction in energy consumption as compared to a home with a HERS Index of 100. A home with a HERS score of 100 reflects a home built to 2006 IEEC Building Codes. See the bottom of this page for more information on HERS scores.",
      "images": [
        "https://res.cloudinary.com/dv0jqjrc3/image/fetch/ar_1.5,c_fill,f_auto,q_auto,w_auto,f_auto,q_auto/https://pultegroup.picturepark.com/Go/sX3iOZau/V/677319/1",
        "https://res.cloudinary.com/dv0jqjrc3/image/fetch/ar_1.5,c_fill,f_auto,q_auto,w_auto,f_auto,q_auto/https://pultegroup.picturepark.com/Go/sX3iOZau/V/677331/1",
        "https://res.cloudinary.com/dv0jqjrc3/image/fetch/ar_1.5,c_fill,f_auto,q_auto,w_auto,f_auto,q_auto/https://pultegroup.picturepark.com/Go/sX3iOZau/V/677332/1",
        "https://res.cloudinary.com/dv0jqjrc3/image/fetch/ar_1.5,c_fill,f_auto,q_auto,w_auto,f_auto,q_auto/https://pultegroup.picturepark.com/Go/sX3iOZau/V/677319/1",
        "https://res.cloudinary.com/dv0jqjrc3/image/fetch/ar_1.5,c_fill,f_auto,q_auto,w_auto,f_auto,q_auto/https://pultegroup.picturepark.com/Go/sX3iOZau/V/677331/1",
        "https://res.cloudinary.com/dv0jqjrc3/image/fetch/ar_1.5,c_fill,f_auto,q_auto,w_auto,f_auto,q_auto/https://pultegroup.picturepark.com/Go/sX3iOZau/V/677332/1"
      ]
    },
    {
      "name": "21244 E 63rd Dr",
      "plan": "Caroline",
      "id": "698415",
      "address": "21244 E 63rd Dr, Aurora, Colorado",
      "price": "$517,990",
      "beds": "3 bd",
      "baths": "2.5 ba",
      "sqft": "1,997 ft²",
      "status": "Available",
      "image_url": "https://res.cloudinary.com/dv0jqjrc3/image/fetch/ar_1.5,c_fill,f_auto,q_auto,g_north,w_132,f_auto,q_auto/https://pultegroup.picturepark.com/Go/3BqWlSa9/V/677325/1",
      "url": "https://www.pulte.com/homes/colorado/denver/aurora/painted-prairie-211358/caroline-698415",
      "latitude": 27.3646311523029,
      "longitude": -82.3959473004829,
      "overview": "ABOUT THE HOME ENERGY RATING SCALE\nThe HERS (Home Energy Rating System) Index allows buyers to compare the relative energy efficiency of different homes. The HERS Index home energy rating is determined by an independent RESNET-certified home energy rater (\"Rater\"). The lower a home&rsquo;s score, the more energy efficient it is in comparison to the HERS referenced home. For every one-point decrease in the HERS Index score, there is a corresponding one percent (1%) reduction in energy consumption as compared to a home with a HERS Index of 100. A home with a HERS score of 100 reflects a home built to 2006 IEEC Building Codes. See the bottom of this page for more information on HERS scores.",
      "images": [
        "https://res.cloudinary.com/dv0jqjrc3/image/fetch/ar_1.5,c_fill,f_auto,q_auto,w_auto,f_auto,q_auto/https://pultegroup.picturepark.com/Go/3BqWlSa9/V/677327/1",
        "https://res.cloudinary.com/dv0jqjrc3/image/fetch/ar_1.5,c_fill,f_auto,q_auto,w_auto,f_auto,q_auto/https://pultegroup.picturepark.com/Go/3BqWlSa9/V/677325/1",
        "https://res.cloudinary.com/dv0jqjrc3/image/fetch/ar_1.5,c_fill,f_auto,q_auto,w_auto,f_auto,q_auto/https://pultegroup.picturepark.com/Go/3BqWlSa9/V/677326/1",
        "https://res.cloudinary.com/dv0jqjrc3/image/fetch/ar_1.5,c_fill,f_auto,q_auto,w_auto,f_auto,q_auto/https://pultegroup.picturepark.com/Go/3BqWlSa9/V/677327/1",
        "https://res.cloudinary.com/dv0jqjrc3/image/fetch/ar_1.5,c_fill,f_auto,q_auto,w_auto,f_auto,q_auto/https://pultegroup.picturepark.com/Go/3BqWlSa9/V/677325/1",
        "https://res.cloudinary.com/dv0jqjrc3/image/fetch/ar_1.5,c_fill,f_auto,q_auto,w_auto,f_auto,q_auto/https://pultegroup.picturepark.com/Go/3BqWlSa9/V/677326/1"
      ]
    }
  ],
  "nearbyplaces": [],
  "collections": []
}