{
  "timestamp": "2025-06-05T15:43:01.613554",
  "name": "Tenaya Springs",
  "status": null,
  "url": "https://www.americanwesthomes.com/homes/nevada/las-vegas/las-vegas/tenaya-springs-211248",
  "price_from": "$495,990",
  "address": "6089 Swift Lariat Street, Las Vegas, Nevada 89139",
  "phone": "(702) 718-0155",
  "description": "ABOUT THE HOME ENERGY RATING SCALE\nThe Residential Energy Services Network (RESNET) developed the Home Energy Rating System (HERS) Index, which is recognized by the EPA and U.S. Department of Energy. The HERS Index is based on a score of 100 for a typical code-built new home. The HERS score is reduced by one point for each percent of reduced energy consumption (i.e., the lower the score, the more energy-efficient the home). A HERS score of 85 is 15% more energy-efficient than a typical new home and 45% more energy-efficient than a typical existing home.",
  "images": [
    "https://res.cloudinary.com/dv0jqjrc3/image/fetch/ar_1.5,c_fill,f_auto,q_auto,w_768/https://pultegroup.cdn.picturepark.com/v/r5CQCpYx/"
  ],
  "location": {
    "latitude": 36.077978,
    "longitude": -115.271813,
    "address": {
      "city": null,
      "state": null,
      "market": null
    }
  },
  "details": {
    "price_range": "$495,990-$521,990",
    "sqft_range": "1,710-2,118",
    "bed_range": "3-4",
    "bath_range": "2.5-3.0",
    "stories_range": null,
    "community_count": 1
  },
  "amenities": [
    {
      "name": "Home Designs",
      "description": "New 2-story Homes",
      "icon_url": null
    },
    {
      "name": "Home Designs",
      "description": "3-Unique Home Designs",
      "icon_url": null
    },
    {
      "name": "Desirable Soutwest",
      "description": "Desirable Soutwest Las Vegas Location",
      "icon_url": null
    },
    {
      "name": "Square Footage",
      "description": "Close proximity to the Blue Diamond Ranch Center and Town Square Las Vegas",
      "icon_url": null
    },
    {
      "name": "Nearby parks",
      "description": "Nearby parks and recreation",
      "icon_url": null
    },
    {
      "name": "Approx. miles",
      "description": "Approx. 10 miles from Harry Reid International Airport",
      "icon_url": null
    },
    {
      "name": "Minutes shopping,",
      "description": "Minutes to shopping, entertainment, outdoor recreation, and desirable schools",
      "icon_url": null
    },
    {
      "name": "Less than",
      "description": "Less than 2 miles from the I-15",
      "icon_url": null
    }
  ],
  "homeplans": [
    {
      "name": "Avondale",
      "url": "https://www.pulte.com/homes/nevada/las-vegas/las-vegas/tenaya-springs-211248/avondale-696759",
      "details": {
        "price": "From $495,990",
        "beds": "3 bd",
        "baths": "2.5 ba",
        "half_baths": null,
        "sqft": "1,710 ft²",
        "status": "Actively selling",
        "image_url": "https://res.cloudinary.com/dv0jqjrc3/image/fetch/ar_1.5,c_fill,f_auto,q_auto,g_north,w_132,f_auto,q_auto/https://pultegroup.picturepark.com/Go/r67zFozO/V/512896/13"
      },
      "floorplan_images": null
    },
    {
      "name": "Lovell",
      "url": "https://www.pulte.com/homes/nevada/las-vegas/las-vegas/tenaya-springs-211248/lovell-696760",
      "details": {
        "price": "From $503,990",
        "beds": "3 bd",
        "baths": "2.5 ba",
        "half_baths": null,
        "sqft": "1,843 ft²",
        "status": "Actively selling",
        "image_url": "https://res.cloudinary.com/dv0jqjrc3/image/fetch/ar_1.5,c_fill,f_auto,q_auto,g_north,w_132,f_auto,q_auto/https://pultegroup.picturepark.com/Go/cu1pzRUQ/V/503633/13"
      },
      "floorplan_images": null
    },
    {
      "name": "Kaufman",
      "url": "https://www.pulte.com/homes/nevada/las-vegas/las-vegas/tenaya-springs-211248/kaufman-696761",
      "details": {
        "price": "From $521,990",
        "beds": "4 bd",
        "baths": "2.5-3 ba",
        "half_baths": null,
        "sqft": "2,118 ft²",
        "status": "Actively selling",
        "image_url": "https://res.cloudinary.com/dv0jqjrc3/image/fetch/ar_1.5,c_fill,f_auto,q_auto,g_north,w_132,f_auto,q_auto/https://pultegroup.cdn.picturepark.com/v/1C4Yhrak/"
      },
      "floorplan_images": null
    }
  ],
  "homesites": [
    {
      "name": null,
      "plan": "Avondale",
      "id": "696759",
      "address": null,
      "price": "$495,990",
      "beds": "3 bd",
      "baths": "2.5 ba",
      "sqft": "1,710 ft²",
      "status": "Available",
      "image_url": "https://res.cloudinary.com/dv0jqjrc3/image/fetch/ar_1.5,c_fill,f_auto,q_auto,g_north,w_132,f_auto,q_auto/https://pultegroup.picturepark.com/Go/r67zFozO/V/512896/13",
      "url": "https://www.pulte.com/homes/nevada/las-vegas/las-vegas/tenaya-springs-211248/avondale-696759",
      "latitude": 27.3646311523029,
      "longitude": -82.3959473004829,
      "overview": "",
      "images": [
        "https://res.cloudinary.com/dv0jqjrc3/image/fetch/ar_1.55,c_fill,f_auto,q_auto,w_auto,f_auto,q_auto/https://www.pulte.com/-/media/pu_family-moving-in-pulte_day3-7928_1920x539_tablet.jpg",
        "https://res.cloudinary.com/dv0jqjrc3/image/fetch/ar_1.55,c_fill,f_auto,q_auto,w_auto,f_auto,q_auto/https://www.pulte.com/-/media/static-picturepark-assets/uncategorized/2022/03/02/02/19/394294-1--pt21411pulteinnovationcampaignwebsitebannergreatoutdoors1920x1240jpg.jpg"
      ]
    },
    {
      "name": null,
      "plan": "Lovell",
      "id": "696760",
      "address": null,
      "price": "$503,990",
      "beds": "3 bd",
      "baths": "2.5 ba",
      "sqft": "1,843 ft²",
      "status": "Available",
      "image_url": "https://res.cloudinary.com/dv0jqjrc3/image/fetch/ar_1.5,c_fill,f_auto,q_auto,g_north,w_132,f_auto,q_auto/https://pultegroup.picturepark.com/Go/cu1pzRUQ/V/503633/13",
      "url": "https://www.pulte.com/homes/nevada/las-vegas/las-vegas/tenaya-springs-211248/lovell-696760",
      "latitude": 27.3646311523029,
      "longitude": -82.3959473004829,
      "overview": "",
      "images": [
        "https://res.cloudinary.com/dv0jqjrc3/image/fetch/ar_1.55,c_fill,f_auto,q_auto,w_auto,f_auto,q_auto/https://www.pulte.com/-/media/pu_family-moving-in-pulte_day3-7928_1920x539_tablet.jpg",
        "https://res.cloudinary.com/dv0jqjrc3/image/fetch/ar_1.55,c_fill,f_auto,q_auto,w_auto,f_auto,q_auto/https://www.pulte.com/-/media/static-picturepark-assets/uncategorized/2022/03/02/02/19/394294-1--pt21411pulteinnovationcampaignwebsitebannergreatoutdoors1920x1240jpg.jpg"
      ]
    },
    {
      "name": null,
      "plan": "Kaufman",
      "id": "696761",
      "address": null,
      "price": "$521,990",
      "beds": "4 bd",
      "baths": "2.5-3 ba",
      "sqft": "2,118 ft²",
      "status": "Available",
      "image_url": "https://res.cloudinary.com/dv0jqjrc3/image/fetch/ar_1.5,c_fill,f_auto,q_auto,g_north,w_132,f_auto,q_auto/https://pultegroup.cdn.picturepark.com/v/1C4Yhrak/",
      "url": "https://www.pulte.com/homes/nevada/las-vegas/las-vegas/tenaya-springs-211248/kaufman-696761",
      "latitude": 27.3646311523029,
      "longitude": -82.3959473004829,
      "overview": "",
      "images": [
        "https://res.cloudinary.com/dv0jqjrc3/image/fetch/ar_1.55,c_fill,f_auto,q_auto,w_auto,f_auto,q_auto/https://www.pulte.com/-/media/pu_family-moving-in-pulte_day3-7928_1920x539_tablet.jpg",
        "https://res.cloudinary.com/dv0jqjrc3/image/fetch/ar_1.55,c_fill,f_auto,q_auto,w_auto,f_auto,q_auto/https://www.pulte.com/-/media/static-picturepark-assets/uncategorized/2022/03/02/02/19/394294-1--pt21411pulteinnovationcampaignwebsitebannergreatoutdoors1920x1240jpg.jpg"
      ]
    }
  ],
  "nearbyplaces": [],
  "collections": []
}