{
  "timestamp": "2025-06-05T02:21:26.749832",
  "name": "The Corners at Cherry Glen",
  "status": null,
  "url": "https://www.pulte.com/homes/michigan/detroit/macomb/the-corners-at-cherry-glen-211187",
  "price_from": "$464,990",
  "address": "20616 West Kilburn Drive, Macomb, Michigan 48044",
  "phone": "(586) 271-7181",
  "description": "ABOUT THE HOME ENERGY RATING SCALE\nThe HERS (Home Energy Rating System) Index allows buyers to compare the relative energy efficiency of different homes. The HERS Index home energy rating is determined by an independent RESNET-certified home energy rater (\"Rater\"). The lower a home&rsquo;s score, the more energy efficient it is in comparison to the HERS referenced home. For every one-point decrease in the HERS Index score, there is a corresponding one percent (1%) reduction in energy consumption as compared to a home with a HERS Index of 100. A home with a HERS score of 100 reflects a home built to 2006 IEEC Building Codes. See the bottom of this page for more information on HERS scores.",
  "images": [
    "https://res.cloudinary.com/dv0jqjrc3/image/fetch/ar_1.5,c_fill,f_auto,q_auto,w_768/https://pultegroup.cdn.picturepark.com/v/RDHC9CC4/"
  ],
  "location": {
    "latitude": 42.671675,
    "longitude": -82.918434,
    "address": {
      "city": null,
      "state": null,
      "market": null
    }
  },
  "details": {
    "price_range": "$464,990-$479,990",
    "sqft_range": "1,766-1,898",
    "bed_range": "2-4",
    "bath_range": "2.0-3.0",
    "stories_range": "2",
    "community_count": 1
  },
  "amenities": [
    {
      "name": "Loft Option",
      "description": "Loft Option Available on All Plans",
      "icon_url": null
    },
    {
      "name": "Home Designs",
      "description": "Modern Home Exteriors",
      "icon_url": null
    },
    {
      "name": "Covered Patio",
      "description": "Covered Patio Options",
      "icon_url": null
    },
    {
      "name": "Home Designs",
      "description": "Private Homesites Available",
      "icon_url": null
    },
    {
      "name": "Community Maintenance",
      "description": "Community Maintenance and Snow Plowing Handled for You",
      "icon_url": null
    },
    {
      "name": "Highly Rated",
      "description": "Highly Rated Chippewa Valley School District",
      "icon_url": null
    },
    {
      "name": "Floor Plans",
      "description": "First Floor Guest & Owner Suites",
      "icon_url": null
    },
    {
      "name": "Home Designs",
      "description": "Large 70' Wide Homesites",
      "icon_url": null
    },
    {
      "name": "Home Designs",
      "description": "100 Available Homesites",
      "icon_url": null
    },
    {
      "name": "Nearby You'll",
      "description": "Nearby You'll Find: Kroger, Costco, Meijer, Nino Salvagio's, Walmart, and More",
      "icon_url": null
    },
    {
      "name": "Central Macomb",
      "description": "Central Macomb Location",
      "icon_url": null
    },
    {
      "name": "Excellently Located",
      "description": "Excellently Located Near M-59",
      "icon_url": null
    },
    {
      "name": "-Mile Radius",
      "description": "5-Mile Radius to Downtown Amenities",
      "icon_url": null
    },
    {
      "name": "Enjoy Macomb",
      "description": "Enjoy Macomb County Community Events Year-Round",
      "icon_url": null
    },
    {
      "name": "Minutes Away",
      "description": "Minutes Away from Entertainment Venues Like MJR Movie Theater",
      "icon_url": null
    }
  ],
  "homeplans": [
    {
      "name": "Alcott",
      "url": "https://www.pulte.com/homes/michigan/detroit/macomb/the-corners-at-cherry-glen-211187/alcott-698232",
      "details": {
        "price": "From $464,990",
        "beds": "2-3 bd",
        "baths": "2-3 ba",
        "half_baths": null,
        "sqft": "1,766+ ft²",
        "status": "Actively selling",
        "image_url": "https://res.cloudinary.com/dv0jqjrc3/image/fetch/ar_1.5,c_fill,f_auto,q_auto,g_north,w_132,f_auto,q_auto/https://pultegroup.picturepark.com/Go/LLAnQjG5/V/637222/1"
      },
      "floorplan_images": [
        {
          "name": "1st Floor Floorplan",
          "url": "https://res.cloudinary.com/dv0jqjrc3/image/fetch/ar_1.0,c_fill,q_auto,f_auto/https://pultegroup.picturepark.com/Go/jH3cBkWc/V/637358/1"
        },
        {
          "name": "2nd Floor Floorplan",
          "url": "https://res.cloudinary.com/dv0jqjrc3/image/fetch/ar_1.0,c_fill,q_auto,f_auto/https://pultegroup.picturepark.com/Go/s7CvYXm8/V/668040/1"
        }
      ]
    },
    {
      "name": "Bedford",
      "url": "https://www.pulte.com/homes/michigan/detroit/macomb/the-corners-at-cherry-glen-211187/bedford-698234",
      "details": {
        "price": "From $474,990",
        "beds": "2-3 bd",
        "baths": "2-3 ba",
        "half_baths": null,
        "sqft": "1,889+ ft²",
        "status": "Actively selling",
        "image_url": "https://res.cloudinary.com/dv0jqjrc3/image/fetch/ar_1.5,c_fill,f_auto,q_auto,g_north,w_132,f_auto,q_auto/https://pultegroup.picturepark.com/Go/HRRnIq57/V/637240/1"
      },
      "floorplan_images": [
        {
          "name": "1st Floor Floorplan",
          "url": "https://res.cloudinary.com/dv0jqjrc3/image/fetch/ar_1.0,c_fill,q_auto,f_auto/https://pultegroup.picturepark.com/Go/R5CSNKIt/V/637359/1"
        },
        {
          "name": "2nd Floor Floorplan",
          "url": "https://res.cloudinary.com/dv0jqjrc3/image/fetch/ar_1.0,c_fill,q_auto,f_auto/https://pultegroup.picturepark.com/Go/zizh9XD0/V/668041/1"
        }
      ]
    },
    {
      "name": "Countryview",
      "url": "https://www.pulte.com/homes/michigan/detroit/macomb/the-corners-at-cherry-glen-211187/countryview-698233",
      "details": {
        "price": "From $479,990",
        "beds": "3-4 bd",
        "baths": "2-3 ba",
        "half_baths": null,
        "sqft": "1,898+ ft²",
        "status": "Actively selling",
        "image_url": "https://res.cloudinary.com/dv0jqjrc3/image/fetch/ar_1.5,c_fill,f_auto,q_auto,g_north,w_132,f_auto,q_auto/https://pultegroup.picturepark.com/Go/HuoehTjN/V/688768/1"
      },
      "floorplan_images": [
        {
          "name": "1st Floor Floorplan",
          "url": "https://res.cloudinary.com/dv0jqjrc3/image/fetch/ar_1.0,c_fill,q_auto,f_auto/https://pultegroup.picturepark.com/Go/laQgjZGd/V/648116/1"
        },
        {
          "name": "2nd Floor Floorplan",
          "url": "https://res.cloudinary.com/dv0jqjrc3/image/fetch/ar_1.0,c_fill,q_auto,f_auto/https://pultegroup.picturepark.com/Go/II2uqAfq/V/668042/1"
        }
      ]
    }
  ],
  "homesites": [
    {
      "name": "20616 West Kilburn Drive",
      "plan": "Alcott",
      "id": "698232",
      "address": "20616 West Kilburn Drive, Macomb, Michigan",
      "price": "$464,990",
      "beds": "2-3 bd",
      "baths": "2-3 ba",
      "sqft": "1,766+ ft²",
      "status": "Available",
      "image_url": "https://res.cloudinary.com/dv0jqjrc3/image/fetch/ar_1.5,c_fill,f_auto,q_auto,g_north,w_132,f_auto,q_auto/https://pultegroup.picturepark.com/Go/LLAnQjG5/V/637222/1",
      "url": "https://www.pulte.com/homes/michigan/detroit/macomb/the-corners-at-cherry-glen-211187/alcott-698232",
      "latitude": 27.3646311523029,
      "longitude": -82.3959473004829,
      "overview": "ABOUT THE HOME ENERGY RATING SCALE\nThe HERS (Home Energy Rating System) Index allows buyers to compare the relative energy efficiency of different homes. The HERS Index home energy rating is determined by an independent RESNET-certified home energy rater (\"Rater\"). The lower a home&rsquo;s score, the more energy efficient it is in comparison to the HERS referenced home. For every one-point decrease in the HERS Index score, there is a corresponding one percent (1%) reduction in energy consumption as compared to a home with a HERS Index of 100. A home with a HERS score of 100 reflects a home built to 2006 IEEC Building Codes. See the bottom of this page for more information on HERS scores.",
      "images": [
        "https://res.cloudinary.com/dv0jqjrc3/image/fetch/ar_1.5,c_fill,f_auto,q_auto,w_auto,f_auto,q_auto/https://pultegroup.picturepark.com/Go/o4qzh5gi/V/671065/1",
        "https://res.cloudinary.com/dv0jqjrc3/image/fetch/ar_1.5,c_fill,f_auto,q_auto,w_auto,f_auto,q_auto/https://pultegroup.picturepark.com/Go/o4qzh5gi/V/671067/1",
        "https://res.cloudinary.com/dv0jqjrc3/image/fetch/ar_1.5,c_fill,f_auto,q_auto,w_auto,f_auto,q_auto/https://pultegroup.picturepark.com/Go/o4qzh5gi/V/671054/1",
        "https://res.cloudinary.com/dv0jqjrc3/image/fetch/ar_1.5,c_fill,f_auto,q_auto,w_auto,f_auto,q_auto/https://pultegroup.picturepark.com/Go/LLAnQjG5/V/637223/1",
        "https://res.cloudinary.com/dv0jqjrc3/image/fetch/ar_1.5,c_fill,f_auto,q_auto,w_auto,f_auto,q_auto/https://pultegroup.picturepark.com/Go/LLAnQjG5/V/637225/1",
        "https://res.cloudinary.com/dv0jqjrc3/image/fetch/ar_1.5,c_fill,f_auto,q_auto,w_auto,f_auto,q_auto/https://pultegroup.picturepark.com/Go/LLAnQjG5/V/637226/1",
        "https://res.cloudinary.com/dv0jqjrc3/image/fetch/ar_1.5,c_fill,f_auto,q_auto,w_auto,f_auto,q_auto/https://pultegroup.picturepark.com/Go/LLAnQjG5/V/637227/1",
        "https://res.cloudinary.com/dv0jqjrc3/image/fetch/ar_1.5,c_fill,f_auto,q_auto,w_auto,f_auto,q_auto/https://pultegroup.picturepark.com/Go/LLAnQjG5/V/637228/1",
        "https://res.cloudinary.com/dv0jqjrc3/image/fetch/ar_1.5,c_fill,f_auto,q_auto,w_auto,f_auto,q_auto/https://pultegroup.picturepark.com/Go/o4qzh5gi/V/671057/1",
        "https://res.cloudinary.com/dv0jqjrc3/image/fetch/ar_1.5,c_fill,f_auto,q_auto,w_auto,f_auto,q_auto/https://pultegroup.picturepark.com/Go/o4qzh5gi/V/671059/1",
        "https://res.cloudinary.com/dv0jqjrc3/image/fetch/ar_1.5,c_fill,f_auto,q_auto,w_auto,f_auto,q_auto/https://pultegroup.picturepark.com/Go/o4qzh5gi/V/671058/1",
        "https://res.cloudinary.com/dv0jqjrc3/image/fetch/ar_1.5,c_fill,f_auto,q_auto,w_auto,f_auto,q_auto/https://pultegroup.picturepark.com/Go/LLAnQjG5/V/637222/1",
        "https://res.cloudinary.com/dv0jqjrc3/image/fetch/ar_1.5,c_fill,f_auto,q_auto,w_auto,f_auto,q_auto/https://pultegroup.picturepark.com/Go/o4qzh5gi/V/671056/1",
        "https://res.cloudinary.com/dv0jqjrc3/image/fetch/ar_1.5,c_fill,f_auto,q_auto,w_auto,f_auto,q_auto/https://pultegroup.picturepark.com/Go/o4qzh5gi/V/671055/1",
        "https://res.cloudinary.com/dv0jqjrc3/image/fetch/ar_1.5,c_fill,f_auto,q_auto,w_auto,f_auto,q_auto/https://pultegroup.picturepark.com/Go/o4qzh5gi/V/671060/1",
        "https://res.cloudinary.com/dv0jqjrc3/image/fetch/ar_1.5,c_fill,f_auto,q_auto,w_auto,f_auto,q_auto/https://pultegroup.picturepark.com/Go/o4qzh5gi/V/671053/1",
        "https://res.cloudinary.com/dv0jqjrc3/image/fetch/ar_1.5,c_fill,f_auto,q_auto,w_auto,f_auto,q_auto/https://pultegroup.picturepark.com/Go/o4qzh5gi/V/671061/1",
        "https://res.cloudinary.com/dv0jqjrc3/image/fetch/ar_1.5,c_fill,f_auto,q_auto,w_auto,f_auto,q_auto/https://pultegroup.picturepark.com/Go/o4qzh5gi/V/671064/1",
        "https://res.cloudinary.com/dv0jqjrc3/image/fetch/ar_1.5,c_fill,f_auto,q_auto,w_auto,f_auto,q_auto/https://pultegroup.picturepark.com/Go/o4qzh5gi/V/671062/1",
        "https://res.cloudinary.com/dv0jqjrc3/image/fetch/ar_1.5,c_fill,f_auto,q_auto,w_auto,f_auto,q_auto/https://pultegroup.picturepark.com/Go/o4qzh5gi/V/671063/1",
        "https://res.cloudinary.com/dv0jqjrc3/image/fetch/ar_1.5,c_fill,f_auto,q_auto,w_auto,f_auto,q_auto/https://pultegroup.picturepark.com/Go/o4qzh5gi/V/671068/1",
        "https://res.cloudinary.com/dv0jqjrc3/image/fetch/ar_1.5,c_fill,f_auto,q_auto,w_auto,f_auto,q_auto/https://pultegroup.picturepark.com/Go/o4qzh5gi/V/671066/1",
        "https://res.cloudinary.com/dv0jqjrc3/image/fetch/ar_1.5,c_fill,f_auto,q_auto,w_auto,f_auto,q_auto/https://pultegroup.picturepark.com/Go/o4qzh5gi/V/671065/1",
        "https://res.cloudinary.com/dv0jqjrc3/image/fetch/ar_1.5,c_fill,f_auto,q_auto,w_auto,f_auto,q_auto/https://pultegroup.picturepark.com/Go/o4qzh5gi/V/671067/1",
        "https://res.cloudinary.com/dv0jqjrc3/image/fetch/ar_1.5,c_fill,f_auto,q_auto,w_auto,f_auto,q_auto/https://pultegroup.picturepark.com/Go/o4qzh5gi/V/671054/1",
        "https://res.cloudinary.com/dv0jqjrc3/image/fetch/ar_1.5,c_fill,f_auto,q_auto,w_auto,f_auto,q_auto/https://pultegroup.picturepark.com/Go/LLAnQjG5/V/637223/1",
        "https://res.cloudinary.com/dv0jqjrc3/image/fetch/ar_1.5,c_fill,f_auto,q_auto,w_auto,f_auto,q_auto/https://pultegroup.picturepark.com/Go/LLAnQjG5/V/637225/1",
        "https://res.cloudinary.com/dv0jqjrc3/image/fetch/ar_1.5,c_fill,f_auto,q_auto,w_auto,f_auto,q_auto/https://pultegroup.picturepark.com/Go/LLAnQjG5/V/637226/1",
        "https://res.cloudinary.com/dv0jqjrc3/image/fetch/ar_1.5,c_fill,f_auto,q_auto,w_auto,f_auto,q_auto/https://pultegroup.picturepark.com/Go/LLAnQjG5/V/637227/1",
        "https://res.cloudinary.com/dv0jqjrc3/image/fetch/ar_1.5,c_fill,f_auto,q_auto,w_auto,f_auto,q_auto/https://pultegroup.picturepark.com/Go/LLAnQjG5/V/637228/1",
        "https://res.cloudinary.com/dv0jqjrc3/image/fetch/ar_1.5,c_fill,f_auto,q_auto,w_auto,f_auto,q_auto/https://pultegroup.picturepark.com/Go/o4qzh5gi/V/671057/1",
        "https://res.cloudinary.com/dv0jqjrc3/image/fetch/ar_1.5,c_fill,f_auto,q_auto,w_auto,f_auto,q_auto/https://pultegroup.picturepark.com/Go/o4qzh5gi/V/671059/1",
        "https://res.cloudinary.com/dv0jqjrc3/image/fetch/ar_1.5,c_fill,f_auto,q_auto,w_auto,f_auto,q_auto/https://pultegroup.picturepark.com/Go/o4qzh5gi/V/671058/1",
        "https://res.cloudinary.com/dv0jqjrc3/image/fetch/ar_1.5,c_fill,f_auto,q_auto,w_auto,f_auto,q_auto/https://pultegroup.picturepark.com/Go/LLAnQjG5/V/637222/1",
        "https://res.cloudinary.com/dv0jqjrc3/image/fetch/ar_1.5,c_fill,f_auto,q_auto,w_auto,f_auto,q_auto/https://pultegroup.picturepark.com/Go/o4qzh5gi/V/671056/1",
        "https://res.cloudinary.com/dv0jqjrc3/image/fetch/ar_1.5,c_fill,f_auto,q_auto,w_auto,f_auto,q_auto/https://pultegroup.picturepark.com/Go/o4qzh5gi/V/671055/1",
        "https://res.cloudinary.com/dv0jqjrc3/image/fetch/ar_1.5,c_fill,f_auto,q_auto,w_auto,f_auto,q_auto/https://pultegroup.picturepark.com/Go/o4qzh5gi/V/671060/1",
        "https://res.cloudinary.com/dv0jqjrc3/image/fetch/ar_1.5,c_fill,f_auto,q_auto,w_auto,f_auto,q_auto/https://pultegroup.picturepark.com/Go/o4qzh5gi/V/671053/1",
        "https://res.cloudinary.com/dv0jqjrc3/image/fetch/ar_1.5,c_fill,f_auto,q_auto,w_auto,f_auto,q_auto/https://pultegroup.picturepark.com/Go/o4qzh5gi/V/671061/1",
        "https://res.cloudinary.com/dv0jqjrc3/image/fetch/ar_1.5,c_fill,f_auto,q_auto,w_auto,f_auto,q_auto/https://pultegroup.picturepark.com/Go/o4qzh5gi/V/671064/1",
        "https://res.cloudinary.com/dv0jqjrc3/image/fetch/ar_1.5,c_fill,f_auto,q_auto,w_auto,f_auto,q_auto/https://pultegroup.picturepark.com/Go/o4qzh5gi/V/671062/1",
        "https://res.cloudinary.com/dv0jqjrc3/image/fetch/ar_1.5,c_fill,f_auto,q_auto,w_auto,f_auto,q_auto/https://pultegroup.picturepark.com/Go/o4qzh5gi/V/671063/1",
        "https://res.cloudinary.com/dv0jqjrc3/image/fetch/ar_1.5,c_fill,f_auto,q_auto,w_auto,f_auto,q_auto/https://pultegroup.picturepark.com/Go/o4qzh5gi/V/671068/1",
        "https://res.cloudinary.com/dv0jqjrc3/image/fetch/ar_1.5,c_fill,f_auto,q_auto,w_auto,f_auto,q_auto/https://pultegroup.picturepark.com/Go/o4qzh5gi/V/671066/1",
        "https://res.cloudinary.com/dv0jqjrc3/image/fetch/ar_1.5,c_fill,f_auto,q_auto,w_auto,f_auto,q_auto/https://pultegroup.picturepark.com/Go/o4qzh5gi/V/671065/1"
      ]
    },
    {
      "name": "20616 West Kilburn Drive",
      "plan": "Bedford",
      "id": "698234",
      "address": "20616 West Kilburn Drive, Macomb, Michigan",
      "price": "$474,990",
      "beds": "2-3 bd",
      "baths": "2-3 ba",
      "sqft": "1,889+ ft²",
      "status": "Available",
      "image_url": "https://res.cloudinary.com/dv0jqjrc3/image/fetch/ar_1.5,c_fill,f_auto,q_auto,g_north,w_132,f_auto,q_auto/https://pultegroup.picturepark.com/Go/HRRnIq57/V/637240/1",
      "url": "https://www.pulte.com/homes/michigan/detroit/macomb/the-corners-at-cherry-glen-211187/bedford-698234",
      "latitude": 27.3646311523029,
      "longitude": -82.3959473004829,
      "overview": "ABOUT THE HOME ENERGY RATING SCALE\nThe HERS (Home Energy Rating System) Index allows buyers to compare the relative energy efficiency of different homes. The HERS Index home energy rating is determined by an independent RESNET-certified home energy rater (\"Rater\"). The lower a home&rsquo;s score, the more energy efficient it is in comparison to the HERS referenced home. For every one-point decrease in the HERS Index score, there is a corresponding one percent (1%) reduction in energy consumption as compared to a home with a HERS Index of 100. A home with a HERS score of 100 reflects a home built to 2006 IEEC Building Codes. See the bottom of this page for more information on HERS scores.",
      "images": [
        "https://res.cloudinary.com/dv0jqjrc3/image/fetch/ar_1.5,c_fill,f_auto,q_auto,w_auto,f_auto,q_auto/https://pultegroup.picturepark.com/Go/iPYz5dl2/V/669127/1",
        "https://res.cloudinary.com/dv0jqjrc3/image/fetch/ar_1.5,c_fill,f_auto,q_auto,w_auto,f_auto,q_auto/https://pultegroup.picturepark.com/Go/HRRnIq57/V/637233/1",
        "https://res.cloudinary.com/dv0jqjrc3/image/fetch/ar_1.5,c_fill,f_auto,q_auto,w_auto,f_auto,q_auto/https://pultegroup.picturepark.com/Go/HRRnIq57/V/637234/1",
        "https://res.cloudinary.com/dv0jqjrc3/image/fetch/ar_1.5,c_fill,f_auto,q_auto,w_auto,f_auto,q_auto/https://pultegroup.picturepark.com/Go/HRRnIq57/V/637235/1",
        "https://res.cloudinary.com/dv0jqjrc3/image/fetch/ar_1.5,c_fill,f_auto,q_auto,w_auto,f_auto,q_auto/https://pultegroup.picturepark.com/Go/HRRnIq57/V/637236/1",
        "https://res.cloudinary.com/dv0jqjrc3/image/fetch/ar_1.5,c_fill,f_auto,q_auto,w_auto,f_auto,q_auto/https://pultegroup.picturepark.com/Go/HRRnIq57/V/637237/1",
        "https://res.cloudinary.com/dv0jqjrc3/image/fetch/ar_1.5,c_fill,f_auto,q_auto,w_auto,f_auto,q_auto/https://pultegroup.picturepark.com/Go/HRRnIq57/V/637238/1",
        "https://res.cloudinary.com/dv0jqjrc3/image/fetch/ar_1.5,c_fill,f_auto,q_auto,w_auto,f_auto,q_auto/https://pultegroup.picturepark.com/Go/HRRnIq57/V/637239/1",
        "https://res.cloudinary.com/dv0jqjrc3/image/fetch/ar_1.5,c_fill,f_auto,q_auto,w_auto,f_auto,q_auto/https://pultegroup.picturepark.com/Go/HRRnIq57/V/637241/1",
        "https://res.cloudinary.com/dv0jqjrc3/image/fetch/ar_1.5,c_fill,f_auto,q_auto,w_auto,f_auto,q_auto/https://pultegroup.picturepark.com/Go/HRRnIq57/V/637242/1",
        "https://res.cloudinary.com/dv0jqjrc3/image/fetch/ar_1.5,c_fill,f_auto,q_auto,w_auto,f_auto,q_auto/https://pultegroup.picturepark.com/Go/HRRnIq57/V/637243/1",
        "https://res.cloudinary.com/dv0jqjrc3/image/fetch/ar_1.5,c_fill,f_auto,q_auto,w_auto,f_auto,q_auto/https://pultegroup.picturepark.com/Go/HRRnIq57/V/637244/1",
        "https://res.cloudinary.com/dv0jqjrc3/image/fetch/ar_1.5,c_fill,f_auto,q_auto,w_auto,f_auto,q_auto/https://pultegroup.picturepark.com/Go/25QeU6jA/V/350561/13",
        "https://res.cloudinary.com/dv0jqjrc3/image/fetch/ar_1.5,c_fill,f_auto,q_auto,w_auto,f_auto,q_auto/https://pultegroup.picturepark.com/Go/iPYz5dl2/V/669123/1",
        "https://res.cloudinary.com/dv0jqjrc3/image/fetch/ar_1.5,c_fill,f_auto,q_auto,w_auto,f_auto,q_auto/https://pultegroup.picturepark.com/Go/iPYz5dl2/V/669121/1",
        "https://res.cloudinary.com/dv0jqjrc3/image/fetch/ar_1.5,c_fill,f_auto,q_auto,w_auto,f_auto,q_auto/https://pultegroup.picturepark.com/Go/HRRnIq57/V/637240/1",
        "https://res.cloudinary.com/dv0jqjrc3/image/fetch/ar_1.5,c_fill,f_auto,q_auto,w_auto,f_auto,q_auto/https://pultegroup.picturepark.com/Go/iPYz5dl2/V/669122/1",
        "https://res.cloudinary.com/dv0jqjrc3/image/fetch/ar_1.5,c_fill,f_auto,q_auto,w_auto,f_auto,q_auto/https://pultegroup.picturepark.com/Go/iPYz5dl2/V/669117/1",
        "https://res.cloudinary.com/dv0jqjrc3/image/fetch/ar_1.5,c_fill,f_auto,q_auto,w_auto,f_auto,q_auto/https://pultegroup.picturepark.com/Go/iPYz5dl2/V/669120/1",
        "https://res.cloudinary.com/dv0jqjrc3/image/fetch/ar_1.5,c_fill,f_auto,q_auto,w_auto,f_auto,q_auto/https://pultegroup.picturepark.com/Go/iPYz5dl2/V/669130/1",
        "https://res.cloudinary.com/dv0jqjrc3/image/fetch/ar_1.5,c_fill,f_auto,q_auto,w_auto,f_auto,q_auto/https://pultegroup.picturepark.com/Go/iPYz5dl2/V/669129/1",
        "https://res.cloudinary.com/dv0jqjrc3/image/fetch/ar_1.5,c_fill,f_auto,q_auto,w_auto,f_auto,q_auto/https://pultegroup.picturepark.com/Go/iPYz5dl2/V/669126/1",
        "https://res.cloudinary.com/dv0jqjrc3/image/fetch/ar_1.5,c_fill,f_auto,q_auto,w_auto,f_auto,q_auto/https://pultegroup.picturepark.com/Go/iPYz5dl2/V/669128/1",
        "https://res.cloudinary.com/dv0jqjrc3/image/fetch/ar_1.5,c_fill,f_auto,q_auto,w_auto,f_auto,q_auto/https://pultegroup.picturepark.com/Go/iPYz5dl2/V/669125/1",
        "https://res.cloudinary.com/dv0jqjrc3/image/fetch/ar_1.5,c_fill,f_auto,q_auto,w_auto,f_auto,q_auto/https://pultegroup.picturepark.com/Go/iPYz5dl2/V/669124/1",
        "https://res.cloudinary.com/dv0jqjrc3/image/fetch/ar_1.5,c_fill,f_auto,q_auto,w_auto,f_auto,q_auto/https://pultegroup.picturepark.com/Go/iPYz5dl2/V/669116/1",
        "https://res.cloudinary.com/dv0jqjrc3/image/fetch/ar_1.5,c_fill,f_auto,q_auto,w_auto,f_auto,q_auto/https://pultegroup.picturepark.com/Go/iPYz5dl2/V/669115/1",
        "https://res.cloudinary.com/dv0jqjrc3/image/fetch/ar_1.5,c_fill,f_auto,q_auto,w_auto,f_auto,q_auto/https://pultegroup.picturepark.com/Go/iPYz5dl2/V/669114/1",
        "https://res.cloudinary.com/dv0jqjrc3/image/fetch/ar_1.5,c_fill,f_auto,q_auto,w_auto,f_auto,q_auto/https://pultegroup.picturepark.com/Go/iPYz5dl2/V/669118/1",
        "https://res.cloudinary.com/dv0jqjrc3/image/fetch/ar_1.5,c_fill,f_auto,q_auto,w_auto,f_auto,q_auto/https://pultegroup.picturepark.com/Go/iPYz5dl2/V/669113/1",
        "https://res.cloudinary.com/dv0jqjrc3/image/fetch/ar_1.5,c_fill,f_auto,q_auto,w_auto,f_auto,q_auto/https://pultegroup.picturepark.com/Go/iPYz5dl2/V/669119/1",
        "https://res.cloudinary.com/dv0jqjrc3/image/fetch/ar_1.5,c_fill,f_auto,q_auto,w_auto,f_auto,q_auto/https://pultegroup.picturepark.com/Go/iPYz5dl2/V/669127/1",
        "https://res.cloudinary.com/dv0jqjrc3/image/fetch/ar_1.5,c_fill,f_auto,q_auto,w_auto,f_auto,q_auto/https://pultegroup.picturepark.com/Go/HRRnIq57/V/637233/1",
        "https://res.cloudinary.com/dv0jqjrc3/image/fetch/ar_1.5,c_fill,f_auto,q_auto,w_auto,f_auto,q_auto/https://pultegroup.picturepark.com/Go/HRRnIq57/V/637234/1",
        "https://res.cloudinary.com/dv0jqjrc3/image/fetch/ar_1.5,c_fill,f_auto,q_auto,w_auto,f_auto,q_auto/https://pultegroup.picturepark.com/Go/HRRnIq57/V/637235/1",
        "https://res.cloudinary.com/dv0jqjrc3/image/fetch/ar_1.5,c_fill,f_auto,q_auto,w_auto,f_auto,q_auto/https://pultegroup.picturepark.com/Go/HRRnIq57/V/637236/1",
        "https://res.cloudinary.com/dv0jqjrc3/image/fetch/ar_1.5,c_fill,f_auto,q_auto,w_auto,f_auto,q_auto/https://pultegroup.picturepark.com/Go/HRRnIq57/V/637237/1",
        "https://res.cloudinary.com/dv0jqjrc3/image/fetch/ar_1.5,c_fill,f_auto,q_auto,w_auto,f_auto,q_auto/https://pultegroup.picturepark.com/Go/HRRnIq57/V/637238/1",
        "https://res.cloudinary.com/dv0jqjrc3/image/fetch/ar_1.5,c_fill,f_auto,q_auto,w_auto,f_auto,q_auto/https://pultegroup.picturepark.com/Go/HRRnIq57/V/637239/1",
        "https://res.cloudinary.com/dv0jqjrc3/image/fetch/ar_1.5,c_fill,f_auto,q_auto,w_auto,f_auto,q_auto/https://pultegroup.picturepark.com/Go/HRRnIq57/V/637241/1",
        "https://res.cloudinary.com/dv0jqjrc3/image/fetch/ar_1.5,c_fill,f_auto,q_auto,w_auto,f_auto,q_auto/https://pultegroup.picturepark.com/Go/HRRnIq57/V/637242/1",
        "https://res.cloudinary.com/dv0jqjrc3/image/fetch/ar_1.5,c_fill,f_auto,q_auto,w_auto,f_auto,q_auto/https://pultegroup.picturepark.com/Go/HRRnIq57/V/637243/1",
        "https://res.cloudinary.com/dv0jqjrc3/image/fetch/ar_1.5,c_fill,f_auto,q_auto,w_auto,f_auto,q_auto/https://pultegroup.picturepark.com/Go/HRRnIq57/V/637244/1",
        "https://res.cloudinary.com/dv0jqjrc3/image/fetch/ar_1.5,c_fill,f_auto,q_auto,w_auto,f_auto,q_auto/https://pultegroup.picturepark.com/Go/25QeU6jA/V/350561/13",
        "https://res.cloudinary.com/dv0jqjrc3/image/fetch/ar_1.5,c_fill,f_auto,q_auto,w_auto,f_auto,q_auto/https://pultegroup.picturepark.com/Go/iPYz5dl2/V/669123/1",
        "https://res.cloudinary.com/dv0jqjrc3/image/fetch/ar_1.5,c_fill,f_auto,q_auto,w_auto,f_auto,q_auto/https://pultegroup.picturepark.com/Go/iPYz5dl2/V/669121/1",
        "https://res.cloudinary.com/dv0jqjrc3/image/fetch/ar_1.5,c_fill,f_auto,q_auto,w_auto,f_auto,q_auto/https://pultegroup.picturepark.com/Go/HRRnIq57/V/637240/1",
        "https://res.cloudinary.com/dv0jqjrc3/image/fetch/ar_1.5,c_fill,f_auto,q_auto,w_auto,f_auto,q_auto/https://pultegroup.picturepark.com/Go/iPYz5dl2/V/669122/1",
        "https://res.cloudinary.com/dv0jqjrc3/image/fetch/ar_1.5,c_fill,f_auto,q_auto,w_auto,f_auto,q_auto/https://pultegroup.picturepark.com/Go/iPYz5dl2/V/669117/1",
        "https://res.cloudinary.com/dv0jqjrc3/image/fetch/ar_1.5,c_fill,f_auto,q_auto,w_auto,f_auto,q_auto/https://pultegroup.picturepark.com/Go/iPYz5dl2/V/669120/1",
        "https://res.cloudinary.com/dv0jqjrc3/image/fetch/ar_1.5,c_fill,f_auto,q_auto,w_auto,f_auto,q_auto/https://pultegroup.picturepark.com/Go/iPYz5dl2/V/669130/1",
        "https://res.cloudinary.com/dv0jqjrc3/image/fetch/ar_1.5,c_fill,f_auto,q_auto,w_auto,f_auto,q_auto/https://pultegroup.picturepark.com/Go/iPYz5dl2/V/669129/1",
        "https://res.cloudinary.com/dv0jqjrc3/image/fetch/ar_1.5,c_fill,f_auto,q_auto,w_auto,f_auto,q_auto/https://pultegroup.picturepark.com/Go/iPYz5dl2/V/669126/1",
        "https://res.cloudinary.com/dv0jqjrc3/image/fetch/ar_1.5,c_fill,f_auto,q_auto,w_auto,f_auto,q_auto/https://pultegroup.picturepark.com/Go/iPYz5dl2/V/669128/1",
        "https://res.cloudinary.com/dv0jqjrc3/image/fetch/ar_1.5,c_fill,f_auto,q_auto,w_auto,f_auto,q_auto/https://pultegroup.picturepark.com/Go/iPYz5dl2/V/669125/1",
        "https://res.cloudinary.com/dv0jqjrc3/image/fetch/ar_1.5,c_fill,f_auto,q_auto,w_auto,f_auto,q_auto/https://pultegroup.picturepark.com/Go/iPYz5dl2/V/669124/1",
        "https://res.cloudinary.com/dv0jqjrc3/image/fetch/ar_1.5,c_fill,f_auto,q_auto,w_auto,f_auto,q_auto/https://pultegroup.picturepark.com/Go/iPYz5dl2/V/669116/1",
        "https://res.cloudinary.com/dv0jqjrc3/image/fetch/ar_1.5,c_fill,f_auto,q_auto,w_auto,f_auto,q_auto/https://pultegroup.picturepark.com/Go/iPYz5dl2/V/669115/1",
        "https://res.cloudinary.com/dv0jqjrc3/image/fetch/ar_1.5,c_fill,f_auto,q_auto,w_auto,f_auto,q_auto/https://pultegroup.picturepark.com/Go/iPYz5dl2/V/669114/1",
        "https://res.cloudinary.com/dv0jqjrc3/image/fetch/ar_1.5,c_fill,f_auto,q_auto,w_auto,f_auto,q_auto/https://pultegroup.picturepark.com/Go/iPYz5dl2/V/669118/1",
        "https://res.cloudinary.com/dv0jqjrc3/image/fetch/ar_1.5,c_fill,f_auto,q_auto,w_auto,f_auto,q_auto/https://pultegroup.picturepark.com/Go/iPYz5dl2/V/669113/1",
        "https://res.cloudinary.com/dv0jqjrc3/image/fetch/ar_1.5,c_fill,f_auto,q_auto,w_auto,f_auto,q_auto/https://pultegroup.picturepark.com/Go/iPYz5dl2/V/669119/1"
      ]
    },
    {
      "name": "20616 West Kilburn Drive",
      "plan": "Countryview",
      "id": "698233",
      "address": "20616 West Kilburn Drive, Macomb, Michigan",
      "price": "$479,990",
      "beds": "3-4 bd",
      "baths": "2-3 ba",
      "sqft": "1,898+ ft²",
      "status": "Available",
      "image_url": "https://res.cloudinary.com/dv0jqjrc3/image/fetch/ar_1.5,c_fill,f_auto,q_auto,g_north,w_132,f_auto,q_auto/https://pultegroup.picturepark.com/Go/HuoehTjN/V/688768/1",
      "url": "https://www.pulte.com/homes/michigan/detroit/macomb/the-corners-at-cherry-glen-211187/countryview-698233",
      "latitude": 27.3646311523029,
      "longitude": -82.3959473004829,
      "overview": "ABOUT THE HOME ENERGY RATING SCALE\nThe HERS (Home Energy Rating System) Index allows buyers to compare the relative energy efficiency of different homes. The HERS Index home energy rating is determined by an independent RESNET-certified home energy rater (\"Rater\"). The lower a home&rsquo;s score, the more energy efficient it is in comparison to the HERS referenced home. For every one-point decrease in the HERS Index score, there is a corresponding one percent (1%) reduction in energy consumption as compared to a home with a HERS Index of 100. A home with a HERS score of 100 reflects a home built to 2006 IEEC Building Codes. See the bottom of this page for more information on HERS scores.",
      "images": [
        "https://res.cloudinary.com/dv0jqjrc3/image/fetch/ar_1.5,c_fill,f_auto,q_auto,w_auto,f_auto,q_auto/https://pultegroup.picturepark.com/Go/4nmrUbSF/V/676989/1",
        "https://res.cloudinary.com/dv0jqjrc3/image/fetch/ar_1.5,c_fill,f_auto,q_auto,w_auto,f_auto,q_auto/https://pultegroup.picturepark.com/Go/4nmrUbSF/V/676991/1",
        "https://res.cloudinary.com/dv0jqjrc3/image/fetch/ar_1.5,c_fill,f_auto,q_auto,w_auto,f_auto,q_auto/https://pultegroup.picturepark.com/Go/8W4AX4gE/V/676983/1",
        "https://res.cloudinary.com/dv0jqjrc3/image/fetch/ar_1.5,c_fill,f_auto,q_auto,w_auto,f_auto,q_auto/https://pultegroup.picturepark.com/Go/4nmrUbSF/V/676996/1",
        "https://res.cloudinary.com/dv0jqjrc3/image/fetch/ar_1.5,c_fill,f_auto,q_auto,w_auto,f_auto,q_auto/https://pultegroup.picturepark.com/Go/4nmrUbSF/V/676997/1",
        "https://res.cloudinary.com/dv0jqjrc3/image/fetch/ar_1.5,c_fill,f_auto,q_auto,w_auto,f_auto,q_auto/https://pultegroup.picturepark.com/Go/4nmrUbSF/V/676994/1",
        "https://res.cloudinary.com/dv0jqjrc3/image/fetch/ar_1.5,c_fill,f_auto,q_auto,w_auto,f_auto,q_auto/https://pultegroup.picturepark.com/Go/4nmrUbSF/V/676995/1",
        "https://res.cloudinary.com/dv0jqjrc3/image/fetch/ar_1.5,c_fill,f_auto,q_auto,w_auto,f_auto,q_auto/https://pultegroup.picturepark.com/Go/8W4AX4gE/V/676964/1",
        "https://res.cloudinary.com/dv0jqjrc3/image/fetch/ar_1.5,c_fill,f_auto,q_auto,w_auto,f_auto,q_auto/https://pultegroup.cdn.picturepark.com/v/2Fq1bpmS/",
        "https://res.cloudinary.com/dv0jqjrc3/image/fetch/ar_1.5,c_fill,f_auto,q_auto,w_auto,f_auto,q_auto/https://pultegroup.cdn.picturepark.com/v/72N59zz3/",
        "https://res.cloudinary.com/dv0jqjrc3/image/fetch/ar_1.5,c_fill,f_auto,q_auto,w_auto,f_auto,q_auto/https://pultegroup.cdn.picturepark.com/v/AkenaVVe/",
        "https://res.cloudinary.com/dv0jqjrc3/image/fetch/ar_1.5,c_fill,f_auto,q_auto,w_auto,f_auto,q_auto/https://pultegroup.picturepark.com/Go/Anw5Ktgx/V/637272/1",
        "https://res.cloudinary.com/dv0jqjrc3/image/fetch/ar_1.5,c_fill,f_auto,q_auto,w_auto,f_auto,q_auto/https://pultegroup.cdn.picturepark.com/v/FI1fJWjk/",
        "https://res.cloudinary.com/dv0jqjrc3/image/fetch/ar_1.5,c_fill,f_auto,q_auto,w_auto,f_auto,q_auto/https://pultegroup.picturepark.com/Go/8W4AX4gE/V/676969/1",
        "https://res.cloudinary.com/dv0jqjrc3/image/fetch/ar_1.5,c_fill,f_auto,q_auto,w_auto,f_auto,q_auto/https://pultegroup.picturepark.com/Go/4nmrUbSF/V/676984/1",
        "https://res.cloudinary.com/dv0jqjrc3/image/fetch/ar_1.5,c_fill,f_auto,q_auto,w_auto,f_auto,q_auto/https://pultegroup.picturepark.com/Go/8W4AX4gE/V/676975/1",
        "https://res.cloudinary.com/dv0jqjrc3/image/fetch/ar_1.5,c_fill,f_auto,q_auto,w_auto,f_auto,q_auto/https://pultegroup.picturepark.com/Go/HuoehTjN/V/688768/1",
        "https://res.cloudinary.com/dv0jqjrc3/image/fetch/ar_1.5,c_fill,f_auto,q_auto,w_auto,f_auto,q_auto/https://pultegroup.picturepark.com/Go/8W4AX4gE/V/676976/1",
        "https://res.cloudinary.com/dv0jqjrc3/image/fetch/ar_1.5,c_fill,f_auto,q_auto,w_auto,f_auto,q_auto/https://pultegroup.picturepark.com/Go/8W4AX4gE/V/676978/1",
        "https://res.cloudinary.com/dv0jqjrc3/image/fetch/ar_1.5,c_fill,f_auto,q_auto,w_auto,f_auto,q_auto/https://pultegroup.picturepark.com/Go/8W4AX4gE/V/676979/1",
        "https://res.cloudinary.com/dv0jqjrc3/image/fetch/ar_1.5,c_fill,f_auto,q_auto,w_auto,f_auto,q_auto/https://pultegroup.picturepark.com/Go/8W4AX4gE/V/676980/1",
        "https://res.cloudinary.com/dv0jqjrc3/image/fetch/ar_1.5,c_fill,f_auto,q_auto,w_auto,f_auto,q_auto/https://pultegroup.picturepark.com/Go/8W4AX4gE/V/676981/1",
        "https://res.cloudinary.com/dv0jqjrc3/image/fetch/ar_1.5,c_fill,f_auto,q_auto,w_auto,f_auto,q_auto/https://pultegroup.picturepark.com/Go/8W4AX4gE/V/676982/1",
        "https://res.cloudinary.com/dv0jqjrc3/image/fetch/ar_1.5,c_fill,f_auto,q_auto,w_auto,f_auto,q_auto/https://pultegroup.picturepark.com/Go/8W4AX4gE/V/676965/1",
        "https://res.cloudinary.com/dv0jqjrc3/image/fetch/ar_1.5,c_fill,f_auto,q_auto,w_auto,f_auto,q_auto/https://pultegroup.picturepark.com/Go/8W4AX4gE/V/676966/1",
        "https://res.cloudinary.com/dv0jqjrc3/image/fetch/ar_1.5,c_fill,f_auto,q_auto,w_auto,f_auto,q_auto/https://pultegroup.picturepark.com/Go/8W4AX4gE/V/676968/1",
        "https://res.cloudinary.com/dv0jqjrc3/image/fetch/ar_1.5,c_fill,f_auto,q_auto,w_auto,f_auto,q_auto/https://pultegroup.picturepark.com/Go/8W4AX4gE/V/676967/1",
        "https://res.cloudinary.com/dv0jqjrc3/image/fetch/ar_1.5,c_fill,f_auto,q_auto,w_auto,f_auto,q_auto/https://pultegroup.picturepark.com/Go/8W4AX4gE/V/676977/1",
        "https://res.cloudinary.com/dv0jqjrc3/image/fetch/ar_1.5,c_fill,f_auto,q_auto,w_auto,f_auto,q_auto/https://pultegroup.picturepark.com/Go/4nmrUbSF/V/676992/1",
        "https://res.cloudinary.com/dv0jqjrc3/image/fetch/ar_1.5,c_fill,f_auto,q_auto,w_auto,f_auto,q_auto/https://pultegroup.picturepark.com/Go/4nmrUbSF/V/676993/1",
        "https://res.cloudinary.com/dv0jqjrc3/image/fetch/ar_1.5,c_fill,f_auto,q_auto,w_auto,f_auto,q_auto/https://pultegroup.picturepark.com/Go/4nmrUbSF/V/676990/1",
        "https://res.cloudinary.com/dv0jqjrc3/image/fetch/ar_1.5,c_fill,f_auto,q_auto,w_auto,f_auto,q_auto/https://pultegroup.picturepark.com/Go/4nmrUbSF/V/676986/1",
        "https://res.cloudinary.com/dv0jqjrc3/image/fetch/ar_1.5,c_fill,f_auto,q_auto,w_auto,f_auto,q_auto/https://pultegroup.picturepark.com/Go/4nmrUbSF/V/676989/1",
        "https://res.cloudinary.com/dv0jqjrc3/image/fetch/ar_1.5,c_fill,f_auto,q_auto,w_auto,f_auto,q_auto/https://pultegroup.picturepark.com/Go/4nmrUbSF/V/676991/1",
        "https://res.cloudinary.com/dv0jqjrc3/image/fetch/ar_1.5,c_fill,f_auto,q_auto,w_auto,f_auto,q_auto/https://pultegroup.picturepark.com/Go/8W4AX4gE/V/676983/1",
        "https://res.cloudinary.com/dv0jqjrc3/image/fetch/ar_1.5,c_fill,f_auto,q_auto,w_auto,f_auto,q_auto/https://pultegroup.picturepark.com/Go/4nmrUbSF/V/676996/1",
        "https://res.cloudinary.com/dv0jqjrc3/image/fetch/ar_1.5,c_fill,f_auto,q_auto,w_auto,f_auto,q_auto/https://pultegroup.picturepark.com/Go/4nmrUbSF/V/676997/1",
        "https://res.cloudinary.com/dv0jqjrc3/image/fetch/ar_1.5,c_fill,f_auto,q_auto,w_auto,f_auto,q_auto/https://pultegroup.picturepark.com/Go/4nmrUbSF/V/676994/1",
        "https://res.cloudinary.com/dv0jqjrc3/image/fetch/ar_1.5,c_fill,f_auto,q_auto,w_auto,f_auto,q_auto/https://pultegroup.picturepark.com/Go/4nmrUbSF/V/676995/1",
        "https://res.cloudinary.com/dv0jqjrc3/image/fetch/ar_1.5,c_fill,f_auto,q_auto,w_auto,f_auto,q_auto/https://pultegroup.picturepark.com/Go/8W4AX4gE/V/676964/1",
        "https://res.cloudinary.com/dv0jqjrc3/image/fetch/ar_1.5,c_fill,f_auto,q_auto,w_auto,f_auto,q_auto/https://pultegroup.cdn.picturepark.com/v/2Fq1bpmS/",
        "https://res.cloudinary.com/dv0jqjrc3/image/fetch/ar_1.5,c_fill,f_auto,q_auto,w_auto,f_auto,q_auto/https://pultegroup.cdn.picturepark.com/v/72N59zz3/",
        "https://res.cloudinary.com/dv0jqjrc3/image/fetch/ar_1.5,c_fill,f_auto,q_auto,w_auto,f_auto,q_auto/https://pultegroup.cdn.picturepark.com/v/AkenaVVe/",
        "https://res.cloudinary.com/dv0jqjrc3/image/fetch/ar_1.5,c_fill,f_auto,q_auto,w_auto,f_auto,q_auto/https://pultegroup.picturepark.com/Go/Anw5Ktgx/V/637272/1",
        "https://res.cloudinary.com/dv0jqjrc3/image/fetch/ar_1.5,c_fill,f_auto,q_auto,w_auto,f_auto,q_auto/https://pultegroup.cdn.picturepark.com/v/FI1fJWjk/",
        "https://res.cloudinary.com/dv0jqjrc3/image/fetch/ar_1.5,c_fill,f_auto,q_auto,w_auto,f_auto,q_auto/https://pultegroup.picturepark.com/Go/8W4AX4gE/V/676969/1",
        "https://res.cloudinary.com/dv0jqjrc3/image/fetch/ar_1.5,c_fill,f_auto,q_auto,w_auto,f_auto,q_auto/https://pultegroup.picturepark.com/Go/4nmrUbSF/V/676984/1",
        "https://res.cloudinary.com/dv0jqjrc3/image/fetch/ar_1.5,c_fill,f_auto,q_auto,w_auto,f_auto,q_auto/https://pultegroup.picturepark.com/Go/8W4AX4gE/V/676975/1",
        "https://res.cloudinary.com/dv0jqjrc3/image/fetch/ar_1.5,c_fill,f_auto,q_auto,w_auto,f_auto,q_auto/https://pultegroup.picturepark.com/Go/HuoehTjN/V/688768/1",
        "https://res.cloudinary.com/dv0jqjrc3/image/fetch/ar_1.5,c_fill,f_auto,q_auto,w_auto,f_auto,q_auto/https://pultegroup.picturepark.com/Go/8W4AX4gE/V/676976/1",
        "https://res.cloudinary.com/dv0jqjrc3/image/fetch/ar_1.5,c_fill,f_auto,q_auto,w_auto,f_auto,q_auto/https://pultegroup.picturepark.com/Go/8W4AX4gE/V/676978/1",
        "https://res.cloudinary.com/dv0jqjrc3/image/fetch/ar_1.5,c_fill,f_auto,q_auto,w_auto,f_auto,q_auto/https://pultegroup.picturepark.com/Go/8W4AX4gE/V/676979/1",
        "https://res.cloudinary.com/dv0jqjrc3/image/fetch/ar_1.5,c_fill,f_auto,q_auto,w_auto,f_auto,q_auto/https://pultegroup.picturepark.com/Go/8W4AX4gE/V/676980/1",
        "https://res.cloudinary.com/dv0jqjrc3/image/fetch/ar_1.5,c_fill,f_auto,q_auto,w_auto,f_auto,q_auto/https://pultegroup.picturepark.com/Go/8W4AX4gE/V/676981/1",
        "https://res.cloudinary.com/dv0jqjrc3/image/fetch/ar_1.5,c_fill,f_auto,q_auto,w_auto,f_auto,q_auto/https://pultegroup.picturepark.com/Go/8W4AX4gE/V/676982/1",
        "https://res.cloudinary.com/dv0jqjrc3/image/fetch/ar_1.5,c_fill,f_auto,q_auto,w_auto,f_auto,q_auto/https://pultegroup.picturepark.com/Go/8W4AX4gE/V/676965/1",
        "https://res.cloudinary.com/dv0jqjrc3/image/fetch/ar_1.5,c_fill,f_auto,q_auto,w_auto,f_auto,q_auto/https://pultegroup.picturepark.com/Go/8W4AX4gE/V/676966/1",
        "https://res.cloudinary.com/dv0jqjrc3/image/fetch/ar_1.5,c_fill,f_auto,q_auto,w_auto,f_auto,q_auto/https://pultegroup.picturepark.com/Go/8W4AX4gE/V/676968/1",
        "https://res.cloudinary.com/dv0jqjrc3/image/fetch/ar_1.5,c_fill,f_auto,q_auto,w_auto,f_auto,q_auto/https://pultegroup.picturepark.com/Go/8W4AX4gE/V/676967/1",
        "https://res.cloudinary.com/dv0jqjrc3/image/fetch/ar_1.5,c_fill,f_auto,q_auto,w_auto,f_auto,q_auto/https://pultegroup.picturepark.com/Go/8W4AX4gE/V/676977/1",
        "https://res.cloudinary.com/dv0jqjrc3/image/fetch/ar_1.5,c_fill,f_auto,q_auto,w_auto,f_auto,q_auto/https://pultegroup.picturepark.com/Go/4nmrUbSF/V/676992/1",
        "https://res.cloudinary.com/dv0jqjrc3/image/fetch/ar_1.5,c_fill,f_auto,q_auto,w_auto,f_auto,q_auto/https://pultegroup.picturepark.com/Go/4nmrUbSF/V/676993/1",
        "https://res.cloudinary.com/dv0jqjrc3/image/fetch/ar_1.5,c_fill,f_auto,q_auto,w_auto,f_auto,q_auto/https://pultegroup.picturepark.com/Go/4nmrUbSF/V/676990/1",
        "https://res.cloudinary.com/dv0jqjrc3/image/fetch/ar_1.5,c_fill,f_auto,q_auto,w_auto,f_auto,q_auto/https://pultegroup.picturepark.com/Go/4nmrUbSF/V/676986/1",
        "https://res.cloudinary.com/dv0jqjrc3/image/fetch/ar_1.5,c_fill,f_auto,q_auto,w_auto,f_auto,q_auto/https://pultegroup.picturepark.com/Go/4nmrUbSF/V/676989/1"
      ]
    }
  ],
  "nearbyplaces": [],
  "collections": []
}